serverhandler/__init__.py
serverhandler-1.2.dist-info/METADATA
serverhandler-1.2.dist-info/WHEEL
serverhandler-1.2.dist-info/top_level.txt
serverhandler-1.2.dist-info/RECORD
