Metadata-Version: 2.1
Name: serverhandler
Version: 1.2
Summary: Used for making online software.
Author: The Figit
Keywords: servers,online,connect,send,receive,chat,handler
